diffo/__about__.py
diffo/__init__.py
diffo/_cli.py
diffo/_paths.py
diffo/_strings.py
diffo-0.1.1.dist-info/METADATA
diffo-0.1.1.dist-info/WHEEL
diffo-0.1.1.dist-info/entry_points.txt
diffo-0.1.1.dist-info/top_level.txt
diffo-0.1.1.dist-info/RECORD
