Metadata-Version: 2.1
Name: diffo
Version: 0.1.1
Summary: Check and show differences between files and folders
Author-email: Nico Schlömer <nico.schloemer@gmail.com>
Project-URL: Homepage, https://github.com/nschloe/diffo
Project-URL: Issues, https://github.com/nschloe/diffo/issues
Classifier: Development Status :: 3 - Alpha
Classifier: License :: Other/Proprietary License
Classifier: Operating System :: OS Independent
Classifier: Programming Language :: Python
Classifier: Programming Language :: Python :: 3
Classifier: Programming Language :: Python :: 3.7
Classifier: Programming Language :: Python :: 3.8
Classifier: Programming Language :: Python :: 3.9
Classifier: Programming Language :: Python :: 3.10
Classifier: Programming Language :: Python :: 3.11
Classifier: Topic :: Text Editors :: Text Processing
Classifier: Topic :: Text Processing
Classifier: Topic :: Utilities
Requires-Python: >=3.7
Requires-Dist: rich
